mfusepy.py
mfusepy-3.1.0.dist-info/licenses/LICENSE
mfusepy-3.1.0.dist-info/METADATA
mfusepy-3.1.0.dist-info/WHEEL
mfusepy-3.1.0.dist-info/top_level.txt
mfusepy-3.1.0.dist-info/RECORD
