Metadata-Version: 2.4
Name: mfusepy
Version: 3.1.0
Summary: Ctypes bindings for the high-level API in libfuse 2 and 3
Author-email: Maximilian Knespel <mxmlnknp@gmail.com>
License: ISC
Project-URL: Homepage, https://github.com/mxmlnkn/mfusepy
Classifier: Development Status :: 4 - Beta
Classifier: Intended Audience :: Developers
Classifier: Operating System :: MacOS
Classifier: Operating System :: POSIX
Classifier: Operating System :: Unix
Classifier: Operating System :: POSIX :: BSD :: FreeBSD
Classifier: Operating System :: POSIX :: BSD :: OpenBSD
Classifier: Programming Language :: Python :: 3
Classifier: Programming Language :: Python :: 3.7
Classifier: Programming Language :: Python :: 3.8
Classifier: Programming Language :: Python :: 3.9
Classifier: Programming Language :: Python :: 3.10
Classifier: Programming Language :: Python :: 3.11
Classifier: Programming Language :: Python :: 3.12
Classifier: Programming Language :: Python :: 3.13
Classifier: Programming Language :: Python :: 3.14
Classifier: Topic :: System :: Filesystems
Requires-Python: >=3.9
License-File: LICENSE
Dynamic: license-file
